Metadata-Version: 2.1
Name: Funnylib
Version: 1.0
Summary: Simple library using https://some-random-api.ml to do so many json operations
Home-page: https://github.com/xKotelek/Funnylib
Author: xKotelek
Author-email: kontakt@kotelek.tk
Classifier: Programming Language :: Python :: 3
Classifier: License :: OSI Approved :: MIT License
Classifier: Operating System :: OS Independent
Requires-Python: >=3.6
